[
  {
    "id": "test",
    "title": "Next.js + MDX でブログを書いています",
    "date": "2020-09-02",
    "tags": ["TypeScript", "React"]
  },
  {
    "id": "test2",
    "title": "Next.js + MDX でブログを書いています",
    "date": "2020-09-02",
    "tags": ["TypeScript", "React"]
  },
  {
    "id": "test3",
    "title": "Next.js + MDX でブログを書いています",
    "date": "2020-09-02",
    "tags": ["TypeScript", "React"]
  },
  {
    "id": "test4",
    "title": "Next.js + MDX でブログを書いています",
    "date": "2020-09-02",
    "tags": ["TypeScript", "React"]
  }
]
